enstools_encoding-2023.6-py3.10-nspkg.pth
enstools/encoding/__init__.py
enstools/encoding/api.py
enstools/encoding/chunk_size.py
enstools/encoding/dataset_encoding.py
enstools/encoding/definitions.py
enstools/encoding/errors.py
enstools/encoding/rules.py
enstools/encoding/variable_encoding.py
enstools_encoding-2023.6.dist-info/LICENSE
enstools_encoding-2023.6.dist-info/METADATA
enstools_encoding-2023.6.dist-info/WHEEL
enstools_encoding-2023.6.dist-info/namespace_packages.txt
enstools_encoding-2023.6.dist-info/top_level.txt
enstools_encoding-2023.6.dist-info/RECORD
