Metadata-Version: 2.1
Name: enstools-encoding
Version: 2023.6
Home-page: https://github.com/wavestoweather/enstools-encoding
Author: Oriol Tintó
Author-email: oriol.tinto@lmu.de
License-File: LICENSE
Requires-Dist: xarray
Requires-Dist: PyYAML
Requires-Dist: h5py
Requires-Dist: h5netcdf
Requires-Dist: hdf5plugin
